suse_udfs_cyy/UDFs.py
suse_udfs_cyy/__init__.py
winpy_plus-0.1.0.dist-info/METADATA
winpy_plus-0.1.0.dist-info/WHEEL
winpy_plus-0.1.0.dist-info/top_level.txt
winpy_plus-0.1.0.dist-info/RECORD
