Metadata-Version: 2.1
Name: winpy-plus
Version: 0.1.0
Summary: A useful tool for extracting data using WindPy
Home-page: 
Author: YaoyuChenWilliam
Author-email: yaoyuchenslm@gmail.com
License: MIT
Classifier: Development Status :: 3 - Alpha
Classifier: Intended Audience :: Developers
Classifier: License :: OSI Approved :: MIT License
Classifier: Programming Language :: Python :: 3
Classifier: Programming Language :: Python :: 3.7
Classifier: Programming Language :: Python :: 3.8
Classifier: Programming Language :: Python :: 3.9
Classifier: Programming Language :: Python :: 3.10
Classifier: Programming Language :: Python :: 3.11
